AUTHORS.rst
CHANGELOG.rst
COPYING.rst
INSTALL.rst
MANIFEST.in
README.rst
TODO.rst
setup.cfg
setup.py
docs/Makefile
docs/api.rst
docs/changelog.rst
docs/conf.py
docs/conf.py.orig
docs/copying.rst
docs/copying_docs.rst
docs/development.rst
docs/index.rst
docs/installation.rst
docs/logging.rst
docs/make.bat
docs/summarizing-text.rst
examples/__init__.py
examples/__init__.pyc
examples/logging_ex.py
examples/summarize.py
textteaser/__init__.py
textteaser/_version.py
textteaser/exceptions.py
textteaser/textteaser.py
textteaser/urls.py
textteaser.egg-info/PKG-INFO
textteaser.egg-info/SOURCES.txt
textteaser.egg-info/dependency_links.txt
textteaser.egg-info/requires.txt
textteaser.egg-info/top_level.txt
textteaser/tests/__init__.py
textteaser/tests/tests.py