Metadata-Version: 1.1
Name: textteaser
Version: 0.3
Summary: A package for summarizing text using the TextTeaser API
Home-page: https://bitbucket.org/jgoettsch/py-textteaser/
Author: Jeffrey Goettsch
Author-email: jgoettsch+pytextteaser@gmail.com
License: UNKNOWN
Download-URL: https://bitbucket.org/jgoettsch/py-textteaser/get/0.3.tar.gz
Platform: UNKNOWN
Classifier: Development Status :: 5 - Production/Stable
Classifier: Intended Audience :: Developers
Classifier: License :: OSI Approved :: GNU Affero General Public License v3 or later (AGPLv3+)
Classifier: Operating System :: OS Independent
Classifier: Programming Language :: Python
Classifier: Programming Language :: Python :: 2
Classifier: Topic :: Software Development
Classifier: Topic :: Software Development :: Libraries
Classifier: Topic :: Software Development :: Libraries :: Python Modules
Classifier: Topic :: Text Processing :: General
